manim_Astronomy/__init__.py
manim_Astronomy/examples.py
manim_Astronomy/main.py
manim_Astronomy/stellar_objects.py
manim_Astronomy-0.0.3.dist-info/LICENSE
manim_Astronomy-0.0.3.dist-info/METADATA
manim_Astronomy-0.0.3.dist-info/WHEEL
manim_Astronomy-0.0.3.dist-info/top_level.txt
manim_Astronomy-0.0.3.dist-info/RECORD
