Metadata-Version: 2.1
Name: manim-Astronomy
Version: 0.0.3
Summary: A Manim extension for creating astronomical visualizations
Home-page: https://github.com/hassamrajpoot/manim-Astronomy
Author: Hassam ul Haq
Author-email: hassamrajpoot100@gmail.com
License: MIT
Classifier: Programming Language :: Python :: 3
Classifier: License :: OSI Approved :: MIT License
Classifier: Operating System :: OS Independent
Requires-Python: >=3.12
License-File: LICENSE
Requires-Dist: manim
Requires-Dist: numpy
Requires-Dist: vedo
